{
    "apps":

     [{
       "app_title": "Ebooks and Audiobooks",
       "app_desc": "Do you like to read ebooks or listen to audiobooks? Test this app!",
       "app_icon": "https://lh3.googleusercontent.com/XVdM31X4Oe5IzQmjCu_ukWLEjcUVBcSOolCa-A-cbp7ivy3VnZED6DCYh1wxSfUDwA=s360-rw",
       "app_header_image": "https://lh3.googleusercontent.com/pePN8tMu7rRK_Rirjc_WSgcziLZaBAk8wY2vXylq7oAddn1jZfd1C6T7t-1bL6ZvAWpV",
       "app_uri": "sanity.learnenglishwithaudiobooks",
       "app_rating": "4.5",
       "app_cta_text": "Install",
       "app_price": "Free",
       "app_adType": "dialog"
     },
     {
       "app_title": "App Name (Dialog)",
       "app_desc": "Your App's description",
       "app_icon": "https://lh3.googleusercontent.com/LNU3wSeIqCtYvvbcklHr4mAQbG4EAVZ_kamQZ_6ECmyYqudAX3FoZy42bIGnSj3pFE5n=s360-rw",
       "app_header_image": "https://lh3.googleusercontent.com/jGNuhkp16zXN5njRuUcEEqeoEtxzyoo2V20r6-gPxRBd01kPDPpTqOEPy1gs33uef5w=w2880-h1438-rw",
       "app_uri": "https://play.google.com/store/apps/details?id=fm.radio.sanity.radiofm",
       "app_rating": "4.5",
       "app_cta_text": "Install",
       "app_price": "Free",
       "app_adType": "interstitial"
     }]
    }